libmwfn.cpython-312-x86_64-linux-gnu.so
libmwfn-0.0.3.dist-info/METADATA
libmwfn-0.0.3.dist-info/WHEEL
libmwfn-0.0.3.dist-info/top_level.txt
libmwfn-0.0.3.dist-info/RECORD
libmwfn-0.0.3.dist-info/licenses/LICENSE
