Metadata-Version: 2.4
Name: libmwfn
Version: 0.0.3
Summary: A flexible .mwfn format handler
Home-page: https://github.com/FreemanTheMaverick/libmwfn.git
Author: FreemanTheMaverick
Classifier: Programming Language :: Python :: 3
License-File: LICENSE
Dynamic: author
Dynamic: classifier
Dynamic: description
Dynamic: description-content-type
Dynamic: home-page
Dynamic: license-file
Dynamic: summary
